coopr.solvers-3.2.1-py2.7-nspkg.pth
coopr/solvers/__init__.py
coopr/solvers/mockmip.py
coopr/solvers/wrappers.py
coopr/solvers/plugins/__init__.py
coopr/solvers/plugins/converter/__init__.py
coopr/solvers/plugins/converter/ampl.py
coopr/solvers/plugins/converter/glpsol.py
coopr/solvers/plugins/converter/pico.py
coopr/solvers/plugins/converter/pyomo.py
coopr/solvers/plugins/smanager/__init__.py
coopr/solvers/plugins/smanager/phpyro.py
coopr/solvers/plugins/smanager/pyro.py
coopr/solvers/plugins/solvers/__init__.py
coopr/solvers/plugins/solvers/ASL.py
coopr/solvers/plugins/solvers/CBCplugin.py
coopr/solvers/plugins/solvers/CPLEX.py
coopr/solvers/plugins/solvers/CPLEXDirect.py
coopr/solvers/plugins/solvers/CPLEXPersistent.py
coopr/solvers/plugins/solvers/GLPK.py
coopr/solvers/plugins/solvers/glpk_direct.py
coopr/solvers/plugins/solvers/GLPK_old.py
coopr/solvers/plugins/solvers/GUROBI.py
coopr/solvers/plugins/solvers/gurobi_direct.py
coopr/solvers/plugins/solvers/GUROBI_RUN.py
coopr/solvers/plugins/solvers/PICO.py
coopr/solvers/plugins/solvers/ps.py
coopr/solvers/plugins/solvers/pywrapper.py
coopr/solvers/plugins/solvers/SCIPAMPL.py
coopr/solvers/plugins/solvers/XPRESS.py
coopr/solvers/plugins/testdriver/__init__.py
coopr/solvers/plugins/testdriver/mip.py
coopr/solvers/plugins/testdriver/pyomo.py
coopr/solvers/tests/__init__.py
coopr/solvers/tests/io/__init__.py
coopr/solvers/tests/io/model_types.py
coopr/solvers/tests/io/test_writers.py
coopr/solvers/tests/io/writer_test_cases.py
coopr/solvers/tests/io/fd/__init__.py
coopr/solvers/tests/mip/__init__.py
coopr/solvers/tests/mip/model.py
coopr/solvers/tests/mip/test_asl.py
coopr/solvers/tests/mip/test_convert.py
coopr/solvers/tests/mip/test_factory.py
coopr/solvers/tests/mip/test_ipopt.py
coopr/solvers/tests/mip/test_mip.py
coopr/solvers/tests/mip/test_solver.py
coopr/solvers/tests/pickling/__init__.py
coopr/solvers/tests/pickling/test_pickle.py
coopr.solvers-3.2.1.dist-info/DESCRIPTION.rst
coopr.solvers-3.2.1.dist-info/METADATA
coopr.solvers-3.2.1.dist-info/metadata.json
coopr.solvers-3.2.1.dist-info/namespace_packages.txt
coopr.solvers-3.2.1.dist-info/RECORD
coopr.solvers-3.2.1.dist-info/top_level.txt
coopr.solvers-3.2.1.dist-info/WHEEL
